.gitignore
CHANGES.txt
LICENSE.txt
MANIFEST.in
README.txt
bootstrap.py
buildout.cfg
setup.py
js/__init__.py
js.spiffform.egg-info/PKG-INFO
js.spiffform.egg-info/SOURCES.txt
js.spiffform.egg-info/dependency_links.txt
js.spiffform.egg-info/entry_points.txt
js.spiffform.egg-info/namespace_packages.txt
js.spiffform.egg-info/not-zip-safe
js.spiffform.egg-info/requires.txt
js.spiffform.egg-info/top_level.txt
js/spiffform/__init__.py
js/spiffform/test_spiffform.txt
js/spiffform/resources/.gitignore
js/spiffform/resources/AUTHORS
js/spiffform/resources/COPYING
js/spiffform/resources/ChangeLog
js/spiffform/resources/README.md
js/spiffform/resources/TODO.txt
js/spiffform/resources/admin.html
js/spiffform/resources/default.css
js/spiffform/resources/form.html
js/spiffform/resources/form.js
js/spiffform/resources/index.html
js/spiffform/resources/lib/jquery-ui.css
js/spiffform/resources/lib/jquery-ui.min.js
js/spiffform/resources/lib/jquery.i18n.min.js
js/spiffform/resources/lib/jquery.min.js
js/spiffform/resources/spiffform/spiffform-de.js
js/spiffform/resources/spiffform/spiffform.js
js/spiffform/resources/spiffform/res/arrow-right.png
js/spiffform/resources/spiffform/res/button.png
js/spiffform/resources/spiffform/res/calendar.png
js/spiffform/resources/spiffform/res/checkbutton.png
js/spiffform/resources/spiffform/res/combo.png
js/spiffform/resources/spiffform/res/entry.png
js/spiffform/resources/spiffform/res/fileselection.png
js/spiffform/resources/spiffform/res/noise.png
js/spiffform/resources/spiffform/res/radio.png
js/spiffform/resources/spiffform/res/separator.png
js/spiffform/resources/spiffform/res/spiffform.css
js/spiffform/resources/spiffform/res/spinbutton.png
js/spiffform/resources/spiffform/res/textview.png