Metadata-Version: 1.0
Name: js.spiffform
Version: 1.0.0
Summary: fanstatic spiffform jQuery.
Home-page: UNKNOWN
Author: Lugensa GmbH
Author-email: jd@lugensa.com
License: BSD
Platform: UNKNOWN
